testcontainers/iris/__init__.py
tests/test_iris.py
testcontainers_iris-1.2.0.dist-info/LICENSE
testcontainers_iris-1.2.0.dist-info/METADATA
testcontainers_iris-1.2.0.dist-info/WHEEL
testcontainers_iris-1.2.0.dist-info/top_level.txt
testcontainers_iris-1.2.0.dist-info/RECORD
