Metadata-Version: 2.2
Name: testcontainers-iris
Version: 1.2.0
Summary: InterSystems IRIS component of testcontainers-python.
Home-page: https://github.com/caretdev/testcontainers-iris-python
Requires-Python: >=3.7
License-File: LICENSE
Requires-Dist: testcontainers
Requires-Dist: sqlalchemy
Requires-Dist: sqlalchemy-iris
Requires-Dist: requests<2.32.0
Dynamic: requires-dist
Dynamic: requires-python
Dynamic: summary
